rollet/__init__.py
rollet/blacklist
rollet/extractor.py
rollet/pdfclient.py
rollet/rollet.py
rollet/runtime.py
rollet/settings.py
rollet/utils.py
rollet-0.1.5.dist-info/LICENSE
rollet-0.1.5.dist-info/METADATA
rollet-0.1.5.dist-info/WHEEL
rollet-0.1.5.dist-info/entry_points.txt
rollet-0.1.5.dist-info/top_level.txt
rollet-0.1.5.dist-info/RECORD
