Metadata-Version: 2.1
Name: rollet
Version: 0.1.5
Summary: Collect data from various sources
Home-page: UNKNOWN
Author: Opscidia (Tech)
Author-email: tech@opscidia.com
Maintainer: Loïc Rakotoson
Maintainer-email: loic.rakotoson@opscidia.com
License: UNKNOWN
Keywords: fetch,pull,extract,scrap
Platform: UNKNOWN
Classifier: Development Status :: 5 - Production/Stable
Classifier: Intended Audience :: Developers
Classifier: Programming Language :: Python :: 3
Classifier: Operating System :: OS Independent
Requires-Python: >=3.7
Requires-Dist: beautifulsoup4 (>=4.9.0)
Requires-Dist: dask
Requires-Dist: pandas
Requires-Dist: tldextract (>=2.2)
Requires-Dist: tqdm
Requires-Dist: requests
